README.md
phylodeep_data_bdei/__init__.py
phylodeep_data_bdei/large/CNN_FULL_TREE.csv.xz
phylodeep_data_bdei/large/FFNN_SUMSTATS.csv.xz
phylodeep_data_bdei/large/target.csv.xz
phylodeep_data_bdei/small/CNN_FULL_TREE.csv.xz
phylodeep_data_bdei/small/FFNN_SUMSTATS.csv.xz
phylodeep_data_bdei/small/target.csv.xz
phylodeep_data_bdei-0.4.dist-info/LICENSE
phylodeep_data_bdei-0.4.dist-info/METADATA
phylodeep_data_bdei-0.4.dist-info/WHEEL
phylodeep_data_bdei-0.4.dist-info/entry_points.txt
phylodeep_data_bdei-0.4.dist-info/top_level.txt
phylodeep_data_bdei-0.4.dist-info/RECORD
